pyicon/__init__.py
pyicon/pyicon_IconData.py
pyicon/pyicon_accessor.py
pyicon/pyicon_calc.py
pyicon/pyicon_calc_xr.py
pyicon/pyicon_params.py
pyicon/pyicon_plotting.py
pyicon/pyicon_simulation.py
pyicon/pyicon_tb.py
pyicon/pyicon_thermo.py
pyicon/version.py
pyicon/quickplots/__init__.py
pyicon/quickplots/old_qp_compare_atm_dwd.py
pyicon/quickplots/old_qp_driver.py
pyicon/quickplots/pyicon_prepare_era.py
pyicon/quickplots/pyicon_quickplots.py
pyicon/quickplots/qp_arctic_budgets.py
pyicon/quickplots/qp_cmaps.py
pyicon/quickplots/qp_compare.py
pyicon/quickplots/qp_compare_atm_dwd.py
pyicon/quickplots/qp_driver.py
pyicon/tests/__init__.py
pyicon/tests/conftest.py
pyicon/tests/test_docs.py
pyicon/tests/test_pyicon_calc_xr.py
pyicon/tests/test_pyicon_plotting.py
pyicon/tests/test_pyicon_thermo.py
pyicon/view/__init__.py
pyicon/view/pyicon_view.py
pyicon/view/pyicon_view_xr.py
scripts/__init__.py
scripts/pyic_anim.py
scripts/pyic_fig.py
scripts/pyic_intake.py
scripts/pyic_sec.py
scripts/pyic_view.py
pyicon_diagnostics-0.4.0.dist-info/LICENSE
pyicon_diagnostics-0.4.0.dist-info/METADATA
pyicon_diagnostics-0.4.0.dist-info/WHEEL
pyicon_diagnostics-0.4.0.dist-info/entry_points.txt
pyicon_diagnostics-0.4.0.dist-info/top_level.txt
pyicon_diagnostics-0.4.0.dist-info/RECORD
