Metadata-Version: 2.1
Name: pyicon-diagnostics
Version: 0.4.0
Summary: Diagnostic python software package for ICON
Home-page: https://gitlab.dkrz.de/m300602/pyicon
Author: The pyicon development team
Author-email: nils.brueggemann@mpimet.mpg.de
Classifier: Programming Language :: Python :: 3
Classifier: License :: OSI Approved :: MIT License
Classifier: Operating System :: OS Independent
License-File: LICENSE
Requires-Dist: numpy
Requires-Dist: matplotlib
Requires-Dist: netcdf4
Requires-Dist: xarray
Requires-Dist: pandas
Requires-Dist: cmocean
Requires-Dist: scipy
Requires-Dist: ipywidgets
Requires-Dist: ipykernel
Requires-Dist: jupytext
Requires-Dist: nbconvert
Requires-Dist: healpy
Requires-Dist: cftime
Requires-Dist: intake
Requires-Dist: requests
Provides-Extra: dev
Requires-Dist: ipdb; extra == "dev"
Requires-Dist: pytest; extra == "dev"
Provides-Extra: doc
Requires-Dist: sphinx; extra == "doc"
Requires-Dist: nbsphinx; extra == "doc"
Requires-Dist: nbsphinx-link; extra == "doc"
Requires-Dist: sphinx-copybutton; extra == "doc"
Requires-Dist: pydata-sphinx-theme; extra == "doc"
Requires-Dist: myst-parser; extra == "doc"
Provides-Extra: full
Requires-Dist: ipdb; extra == "full"
Requires-Dist: pytest; extra == "full"
Requires-Dist: sphinx; extra == "full"
Requires-Dist: nbsphinx; extra == "full"
Requires-Dist: nbsphinx-link; extra == "full"
Requires-Dist: sphinx-copybutton; extra == "full"
Requires-Dist: pydata-sphinx-theme; extra == "full"
Requires-Dist: myst-parser; extra == "full"
